{"inkVersion":21,"root":[["^Sorry, that took a bit longer than expected. I hope you found some way to entertain yourself whilst I was away.","\n","ev","str","^Not really","/str","/ev",{"*":"0.c-0","flg":20},"ev","str","^I looked around your room a bit","/str","/ev",{"*":"0.c-1","flg":20},{"c-0":["\n","ev",{"f()":"NeutralResponse"},"pop","/ev","\n","^No? Now I feel bad for leaving you here for so long. Oh, ",{"->":"Basil"},"\n",{"->":"0.g-0"},{"#f":5}],"c-1":["\n","ev",{"f()":"SmileResponse"},"pop","/ev","\n","^Did you find anything that peaked your interest?","\n",["ev","str","^Your dog is really cute","/str","/ev",{"*":".^.c-0","flg":20},"ev","str","^I found a few items of interest","/str","/ev",{"*":".^.c-1","flg":20},{"c-0":["\n","ev",{"f()":"HappyResponse"},"pop","/ev","\n","^Oh, ",{"->":"Basil"},"\n",{"->":"0.g-0"},{"#f":5}],"c-1":["\n","^Would you like to know more about any item? ",{"->":"Items"},"\n",{"->":"0.g-0"},{"#f":5}]}],{"#f":5}],"g-0":["done",{"#f":5}]}],"done",{"Basil":[["^Did you pet Basil?","\n","ev","str","^Basil?","/str","/ev",{"*":".^.c-0","flg":20},{"c-0":["\n","^Ah, yeah I forgot to tell you, Basil is the name of my dog. The little cutie over there in her dogbed.","\n",["ev","str","^Aw, that's her name!","/str","/ev",{"*":".^.c-0","flg":20},"ev","str","^What kind of name is Basil..?","/str","/ev",{"*":".^.c-1","flg":20},{"c-0":["\n","ev",{"f()":"HappyResponse"},"pop","/ev","\n","^I know it's not the most usual, but it was the first plant I got when I moved here, so it has a special place in my heart, just like her.","\n",["ev","str","^That's a wierd story","/str","/ev",{"*":".^.c-0","flg":20},"ev","str","^That's really sweet","/str","/ev",{"*":".^.c-1","flg":20},{"c-0":["\n","ev",{"f()":"NeutralResponse"},"pop","/ev","\n","^I guess it can be viewed as such. Since you say you didn't look around that much, would you like me to give you a brief tour of some of the things I have?","\n",["ev","str","^Yeah, that would be nice","/str","/ev",{"*":".^.c-0","flg":20},"ev","str","^Not really","/str","/ev",{"*":".^.c-1","flg":20},{"c-0":["\n","ev",{"f()":"HappyResponse"},"pop","/ev","\n","^What would you like to know more about? ",{"->":"Items"},"\n",{"#f":5}],"c-1":["\n","ev",{"f()":"AnnoyedResponse"},"pop","/ev","\n","^Are you sure? There is nothing you would like to know about? ",{"->":"Items"},"\n",{"#f":5}]}],{"#f":5}],"c-1":["\n","ev",{"f()":"SmileResponse"},"pop","/ev","\n","^I'm glad you think so, Since you say you didn't look around that much, would you like me to give you a brief tour of some of the things I have?","\n",["ev","str","^Yeah, That would be nice","/str","/ev",{"*":".^.c-0","flg":20},"ev","str","^Not really","/str","/ev",{"*":".^.c-1","flg":20},{"c-0":["\n","ev",{"f()":"HappyResponse"},"pop","/ev","\n","^What would you like to know more about? ",{"->":"Items"},"\n",{"#f":5}],"c-1":["\n","ev",{"f()":"AnnoyedResponse"},"pop","/ev","\n","^Are you sure? There is nothing you would like to know about? ",{"->":"Items"},"\n",{"#f":5}]}],{"#f":5}]}],{"#f":5}],"c-1":["\n","ev",{"f()":"SmileResponse"},"pop","/ev","\n","^I know it's not the most usual, but it was the first plant I got when I moved here, so it has a special place in my heart, just like her.","\n",["ev","str","^Oh, Did you move recently","/str","/ev",{"*":".^.c-0","flg":20},"ev","str","^Still a weird name","/str","/ev",{"*":".^.c-1","flg":20},{"c-0":["\n","ev",{"f()":"HappyResponse"},"pop","/ev","\n","^I did actually. Oh, since you say you didn't look around that much, would you like me to give you a brief tour of some of the things I have?","\n",["ev","str","^Yeah, that would be nice","/str","/ev",{"*":".^.c-0","flg":20},"ev","str","^Not really","/str","/ev",{"*":".^.c-1","flg":20},{"c-0":["\n","ev",{"f()":"HappyResponse"},"pop","/ev","\n","^What would you like to know more about? ",{"->":"Items"},"\n",{"#f":5}],"c-1":["\n","ev",{"f()":"AnnoyedResponse"},"pop","/ev","\n","^Are you sure? There is nothing you would like to know about? ",{"->":"Items"},"\n",{"#f":5}]}],{"#f":5}],"c-1":["\n","ev",{"f()":"AnnoyedResponse"},"pop","/ev","\n","^Maybe, but weird does not always have to mean bad. Oh, since you say you didn't look around that much, would you like me to give you a brief tour of some of the things I have?","\n",["ev","str","^Yeah, That would be nice","/str","/ev",{"*":".^.c-0","flg":20},"ev","str","^Not really","/str","/ev",{"*":".^.c-1","flg":20},{"c-0":["\n","ev",{"f()":"HappyResponse"},"pop","/ev","\n","^What would you like to know more about? ",{"->":"Items"},"\n",{"#f":5}],"c-1":["\n","ev",{"f()":"AnnoyedResponse"},"pop","/ev","\n","^Are you sure? There is nothing you would like to know about? ",{"->":"Items"},"\n",{"#f":5}]}],{"#f":5}]}],{"#f":5}]}],{"#f":5}]}],{"#f":1}],"Items":[["ev","str","^ Microscope","/str","/ev",{"*":".^.c-0","flg":20},"ev","str","^The Smiths poster ","/str","/ev",{"*":".^.c-1","flg":20},{"c-0":["\n","ev",{"f()":"AnnoyedResponse"},"pop","/ev","\n","^Ah, I would prefer if you refrained from touching that, simply because it is quite a complex piece of equipment.","\n",["ev","str","^You think I'm too stupid to understand it?","/str","/ev",{"*":".^.c-0","flg":20},"ev","str","^I was being careful...","/str","/ev",{"*":".^.c-1","flg":20},{"c-0":["\n","ev",{"f()":"AnnoyedResponse"},"pop","/ev","\n","^No? It is simply not something people know how to operate. As long as you didn't change any settings it should be fine.","\n",["ev","str","^And what if i did mess with the settings?","/str","/ev",{"*":".^.c-0","flg":20},{"c-0":["\n","ev",{"f()":"NegativeResponse"},"pop","/ev","\n","^...Why would you mess with someones stuff like that?","\n",["ev","str","^You are the one who left me alone","/str","/ev",{"*":".^.c-0","flg":20},"ev","str","^I didn't actually mess with it","/str","/ev",{"*":".^.c-1","flg":20},{"c-0":["\n","ev",{"f()":"AnnoyedResponse"},"pop","/ev","\n","^I thought I could trust you to atleast not break anything whilst I was getting us something to drink.","\n",["ev","str","^I wanted to see your reaction","/str","/ev",{"*":".^.c-0","flg":20},"ev","str","^I thought it would be funny","/str","/ev",{"*":".^.c-1","flg":20},{"c-0":["\n","ev",{"f()":"NegativeResponse"},"pop","/ev","\n","^See my reaction? Where you really so bored in the 5 minutes I left that you felt the need to aggrevate me?","\n",["ev","str","^...Now that you say it it was kinda stupid","/str","/ev",{"*":".^.c-0","flg":20},"ev","str","^I thought it would be funny","/str","/ev",{"*":".^.c-1","flg":20},{"c-0":["\n","ev",{"f()":"NeutralResponse"},"pop","/ev","\n","^As long as you don't do it again I suppose. ",{"->":"toughConvo"},"\n",{"#f":5}],"c-1":["\n","ev",{"f()":"AnnoyedResponse"},"pop","/ev","\n","^You thought it would be funny to provoke me? ",{"->":"Arguing"},"\n",{"#f":5}]}],{"#f":5}],"c-1":["\n","ev",{"f()":"AnnoyedResponse"},"pop","/ev","\n","^You thought it wold be funny to mess with and potentially break my stuff? ",{"->":"Arguing"},"\n",{"#f":5}]}],{"#f":5}],"c-1":["\n","ev",{"f()":"NeutralResponse"},"pop","/ev","\n","^Oh...Then why would you say that you did?","\n",["ev","str","^I wanted to see your reaction","/str","/ev",{"*":".^.c-0","flg":20},"ev","str","^I thought it would be funny","/str","/ev",{"*":".^.c-1","flg":20},{"c-0":["\n","ev",{"f()":"NegativeResponse"},"pop","/ev","\n","^See my reaction? Where you really so bored in the 5 minutes I left that you felt the need to aggrevate me?","\n",["ev","str","^...Now that you say it it was kinda stupid","/str","/ev",{"*":".^.c-0","flg":20},"ev","str","^I thought it would be funny","/str","/ev",{"*":".^.c-1","flg":20},{"c-0":["\n","ev",{"f()":"NeutralResponse"},"pop","/ev","\n","^As long as you don't do it again I suppose. ",{"->":"toughConvo"},"\n",{"#f":5}],"c-1":["\n","ev",{"f()":"AnnoyedResponse"},"pop","/ev","\n","^You thought it would be funny to provoke me? ",{"->":"Arguing"},"\n",{"#f":5}]}],{"#f":5}],"c-1":["\n","ev",{"f()":"AnnoyedResponse"},"pop","/ev","\n","^You thought it would be funny to say that you purposefully messed with and potentially destroyed my stuff? ",{"->":"Arguing"},"\n",{"#f":5}]}],{"#f":5}]}],{"#f":5}]}],{"#f":5}],"c-1":["\n","ev",{"f()":"NeutralResponse"},"pop","/ev","\n","^I suppose I should have put it away if I didn't want you to touch it.","\n",["ev","str","^So no harm done?","/str","/ev",{"*":".^.c-0","flg":20},{"c-0":["\n","ev",{"f()":"HappyResponse"},"pop","/ev","\n","^No, luckily not. If you are that interested in it I could teach you how to use it sometime?","\n",["ev","str","^Not really","/str","/ev",{"*":".^.c-0","flg":20},"ev","str","^That would be nice","/str","/ev",{"*":".^.c-1","flg":20},{"c-0":["\n","ev",{"f()":"NeutralResponse"},"pop","/ev","\n","^That's understandable, it's not for everyone. ",{"->":"toughConvo"},"\n",{"#f":5}],"c-1":["\n","ev",{"f()":"EmbarrassedResponse"},"pop","/ev","\n","^Then I look forward to having someone like you as my student. I feel like I should warn you that I can get quite absorbed in the subject, so feel free to cut off my rambles.","\n",["ev","str","^I think I'll let you ramble","/str","/ev",{"*":".^.c-0","flg":20},"ev","str","^Don't worry I'll cut you off","/str","/ev",{"*":".^.c-1","flg":20},{"c-0":["\n","ev",{"f()":"HappyResponse"},"pop","/ev","\n","^Well, if you like to listen then I think we will make for a stellar team. ",{"->":"toughConvo"},"\n",{"#f":5}],"c-1":["\n","ev",{"f()":"NeutralResponse"},"pop","/ev","\n","^That's good, atleast one of us can be responsible and get stuff done then. ",{"->":"toughConvo"},"\n",{"#f":5}]}],{"#f":5}]}],{"#f":5}]}],{"#f":5}]}],{"#f":5}],"c-1":["\n","ev",{"f()":"NeutralResponse"},"pop","/ev","\n","^Oh, You also like The Smiths? I think their music has a sort of passion that is hard to come by these days.","\n",["ev","str","^Yeah, I really like rock","/str","/ev",{"*":".^.c-0","flg":20},"ev","str","^Rock is not really my thing","/str","/ev",{"*":".^.c-1","flg":20},{"c-0":["\n","ev",{"f()":"HappyResponse"},"pop","/ev","\n","^Me too, it really does wonders for soothing the soul on a bad day.","\n",["ev","str","^It really does!","/str","/ev",{"*":".^.c-0","flg":20},"ev","str","^Rock...soothes the soul?","/str","/ev",{"*":".^.c-1","flg":20},{"c-0":["\n","ev",{"f()":"SmileResponse"},"pop","/ev","\n","^Oh, you agree? I thought Maybe it's because it helped me through a tougher time in life , I might be biased. I'm glad to know someone shares the sentiment.","\n",["ev","str","^Biased?","/str","/ev",{"*":".^.c-0","flg":20},"ev","str","^Tougher time in life?","/str","/ev",{"*":".^.c-1","flg":20},{"c-0":["\n","^...Yeah ",{"->":"toughConvo"},"\n",{"#f":5}],"c-1":["\n","^..Yeah ",{"->":"toughConvo"},"\n",{"#f":5}]}],{"#f":5}],"c-1":["\n","ev",{"f()":"NeutralResponse"},"pop","/ev","\n","^Hmm, you disagrew? Maybe it's because it helped me through a tougher time in life , I might be biased.","\n",["ev","str","^Biased?","/str","/ev",{"*":".^.c-0","flg":20},"ev","str","^Tougher time in life?","/str","/ev",{"*":".^.c-1","flg":20},{"c-0":["\n","^...Yeah ",{"->":"toughConvo"},"\n",{"#f":5}],"c-1":["\n","^...Yeah ",{"->":"toughConvo"},"\n",{"#f":5}]}],{"#f":5}]}],{"#f":5}],"c-1":["\n","ev",{"f()":"NeutralResponse"},"pop","/ev","\n","^I guess it's not for everyone, I think it really does wonders to sooth the soul.","\n",["ev","str","^I don't really get it","/str","/ev",{"*":".^.c-0","flg":20},"ev","str","^Rock...soothes the soul?","/str","/ev",{"*":".^.c-1","flg":20},{"c-0":["\n","ev",{"f()":"NeutralResponse"},"pop","/ev","\n","^Hmm, you disagree? Maybe it's because it helped me through a tougher time in life , I might be biased.","\n",["ev","str","^Biased?","/str","/ev",{"*":".^.c-0","flg":20},"ev","str","^Tougher time in life?","/str","/ev",{"*":".^.c-1","flg":20},{"c-0":["\n","^...Yeah ",{"->":"toughConvo"},"\n",{"#f":5}],"c-1":["\n","^..Yeah ",{"->":"toughConvo"},"\n",{"#f":5}]}],{"#f":5}],"c-1":["\n","ev",{"f()":"NeutralResponse"},"pop","/ev","\n","^Hmm, you disagree? Maybe it's because it helped me through a tougher time in life , I might be biased.","\n",["ev","str","^Biased?","/str","/ev",{"*":".^.c-0","flg":20},"ev","str","^Tougher time in life?","/str","/ev",{"*":".^.c-1","flg":20},{"c-0":["\n","^...Yeah ",{"->":"toughConvo"},"\n",{"#f":5}],"c-1":["\n","^..Yeah ",{"->":"toughConvo"},"\n",{"#f":5}]}],{"#f":5}]}],{"#f":5}]}],{"#f":5}]}],{"#f":1}],"Arguing":[["^Do you really get this much entertainment out of picking a fight?","\n","ev","str","^Well I'm not the only one fighting am I?","/str","/ev",{"*":".^.c-0","flg":20},"ev","str","^It's very entertaining","/str","/ev",{"*":".^.c-1","flg":20},{"c-0":["\n","ev",{"f()":"NegativeResponse"},"pop","/ev","\n","^No but you are the one that keeps them going. Have I done something wrong?","\n",["ev","str","^Maybe I just wan't to fight to fight","/str","/ev",{"*":".^.c-0","flg":20},"ev","str","^You keep insinuating that I'm incompetent","/str","/ev",{"*":".^.c-1","flg":20},{"c-0":["\n","ev",{"f()":"AnnoyedResponse"},"pop","/ev","\n","^Seriously?! This is exactly what I mean. What do you have against me?","\n",["ev","str","^You keep calling my stupid one way or another!","/str","/ev",{"*":".^.c-0","flg":20},{"c-0":["\n","ev",{"f()":"AnnoyedResponse"},"pop","/ev","\n","^Maybe because you act like it? You say you mess with my stuff, and after I explain how important it is to me, you tell me the only reason you did it was cause my reaction would be funny?","\n",["ev","str","^ Well, your reaction is a major redflag so...","/str","/ev",{"*":".^.c-0","flg":20},"ev","str","^Was I wrong?","/str","/ev",{"*":".^.c-1","flg":20},"ev","str","^Turns out I don't like nonbinary people","/str","/ev",{"*":".^.c-2","flg":20},{"c-0":["\n","ev",{"f()":"Death"},"pop","/ev","\n","^That's it, I've had enough of you, just leave. ","end","\n",{"#f":5}],"c-1":["\n","ev",{"f()":"Death"},"pop","/ev","\n","^That's it, I've had enough of you, just leave. ","end","\n",{"#f":5}],"c-2":["\n","ev",{"f()":"NegativeResponse"},"pop","/ev","\n","^...Are you being serious right now?","\n",["ev","str","^Yes","/str","/ev",{"*":".^.c-0","flg":20},"ev","str","^No","/str","/ev",{"*":".^.c-1","flg":20},{"c-0":["\n","ev",{"f()":"Death"},"pop","/ev","\n","^Have you have really been fucking with me all this time? Did you ever care or was this all just som experiment to you? Get out. ","end","\n",{"#f":5}],"c-1":["\n","ev",{"f()":"Death"},"pop","/ev","\n","^Have you have really been fucking with me all this time? Did you ever care or was this all jus som experiment to you? Get out. ","end","\n",{"#f":5}]}],{"#f":5}]}],{"#f":5}]}],{"#f":5}],"c-1":["\n","ev",{"f()":"AnnoyedResponse"},"pop","/ev","\n","^Maybe because you act like it? You say you mess with my stuff, and after I explain how important it is to me, you tell me the only reason you did it was cause my reaction would be funny?","\n",["ev","str","^ Well, your reaction is a major redflag so...","/str","/ev",{"*":".^.c-0","flg":20},"ev","str","^Was I wrong?","/str","/ev",{"*":".^.c-1","flg":20},{"c-0":["\n","ev",{"f()":"Death"},"pop","/ev","\n","^That's it, I've had enough of you, just leave. ","end","\n",{"#f":5}],"c-1":["\n","ev",{"f()":"Death"},"pop","/ev","\n","^That's it, I've had enough of you, just leave. ","end","\n",{"#f":5}]}],{"#f":5}]}],{"#f":5}],"c-1":["\n","ev",{"f()":"NegativeResponse"},"pop","/ev","\n","^Have I done something wrong?","\n",["ev","str","^Maybe I just wan't to fight to fight","/str","/ev",{"*":".^.c-0","flg":20},"ev","str","^You keep insinuating that I'm incompetent","/str","/ev",{"*":".^.c-1","flg":20},{"c-0":["\n","ev",{"f()":"AnnoyedResponse"},"pop","/ev","\n","^Seriously?! This is exactly what I mean. What do you have against me?","\n",["ev","str","^You keep calling my stupid one way or another!","/str","/ev",{"*":".^.c-0","flg":20},{"c-0":["\n","ev",{"f()":"AnnoyedResponse"},"pop","/ev","\n","^Maybe Bbcause you act like it? You say you mess with my stuff, and after I explain how important it is to me, you tell me the only reason you did it was cause my reaction would be funny?","\n",["ev","str","^ Well, your reaction is a majoy redflag so...","/str","/ev",{"*":".^.c-0","flg":20},"ev","str","^Was I wrong?","/str","/ev",{"*":".^.c-1","flg":20},"ev","str","^Turns out I don't like nonbinary people","/str","/ev",{"*":".^.c-2","flg":20},{"c-0":["\n","ev",{"f()":"Death"},"pop","/ev","\n","^That's it, I've had enough of you, just leave. ","end","\n",{"#f":5}],"c-1":["\n","ev",{"f()":"Death"},"pop","/ev","\n","^That's it, I've had enough of you, just leave. ","end","\n",{"#f":5}],"c-2":["\n","ev",{"f()":"NegativeResponse"},"pop","/ev","\n","^...Are you being serious righ now?","\n",["ev","str","^Yes","/str","/ev",{"*":".^.c-0","flg":20},"ev","str","^No","/str","/ev",{"*":".^.c-1","flg":20},{"c-0":["\n","ev",{"f()":"Death"},"pop","/ev","\n","^Have you have really been fucking with me all this time? Did you ever care or was this all jus som experiment to you? Get out. ","end","\n",{"#f":5}],"c-1":["\n","ev",{"f()":"Death"},"pop","/ev","\n","^Have you have really been fucking with me all this time? Did you ever care or was this all jus som experiment to you? Get out. ","end","\n",{"#f":5}]}],{"#f":5}]}],{"#f":5}]}],{"#f":5}],"c-1":["\n","ev",{"f()":"AnnoyedResponse"},"pop","/ev","\n","^Maybe because you act like it? You say you mess with my stuff, and after I explain how important it is to me, you tell me the only reason you did it was cause my reaction would be funny?","\n",["ev","str","^ Well, your reaction is a major redflag so...","/str","/ev",{"*":".^.c-0","flg":20},"ev","str","^Was I wrong?","/str","/ev",{"*":".^.c-1","flg":20},{"c-0":["\n","ev",{"f()":"Death"},"pop","/ev","\n","^That's it, I've had enough of you, just leave. ","end","\n",{"#f":5}],"c-1":["\n","ev",{"f()":"Death"},"pop","/ev","\n","^That's it, I've had enough of you, just leave. ","end","\n",{"#f":5}]}],{"#f":5}]}],{"#f":5}]}],{"#f":1}],"toughConvo":[["^I only just moved here in a hurry so unfortunately I dont have a lot of stuff unpack...","\n","ev","str","^In a hurry?","/str","/ev",{"*":".^.c-0","flg":20},"ev","str","^You're also new to the area?","/str","/ev",{"*":".^.c-1","flg":20},{"c-0":["\n","ev",{"f()":"SmileResponse"},"pop","/ev","\n","^Ah, yeah, I was living at home to save some cash, but my parents made it impossible to live with them because of our conflicting beliefs. ",{"->":"Parents"},"\n",{"#f":5}],"c-1":["\n","ev",{"f()":"SmileResponse"},"pop","/ev","\n","^Ah, yeah I was living at home to save some cash, but my parents made it impossible to live with them beacue of our conflicting belifes. ",{"->":"Parents"},"\n",{"#f":5}]}],{"#f":1}],"Parents":[["ev","str","^Oh are you religious?","/str","/ev",{"*":".^.c-0","flg":20},"ev","str","^Couldn't take it","/str","/ev",{"*":".^.c-1","flg":20},{"c-0":["\n","^Haha, No I wouldn’t say so. They just couldn’t handle the fact that I wanted to identify outside of the binary.","\n",["ev","str","^Outside the binary?","/str","/ev",{"*":".^.c-0","flg":20},"ev","str","^They didn’t accept that your nonbinary?","/str","/ev",{"*":".^.c-1","flg":20},{"c-0":["\n","ev",{"f()":"AnnoyedResponse"},"pop","/ev","\n","^Do I have to spell it out for you? I mean it is in my bio? I’m nonbinary.","\n",["ev","str","^Oh, you're one of those","/str","/ev",{"*":".^.c-0","flg":20},{"c-0":["\n","ev",{"f()":"NegativeResponse"},"pop","/ev","\n","^Excuse me, 'one of those'? What’s that supposed to mean?","\n",["ev","str","^Ah, I’m sorry that came out wrong","/str","/ev",{"*":".^.c-0","flg":20},"ev","str","^Exactly what it sounds like.","/str","/ev",{"*":".^.c-1","flg":20},{"c-0":["^ ","\n","ev",{"f()":"AnnoyedResponse"},"pop","/ev","\n","^It's fine. I think it's best we part ways for today. Send me a message if you wanna meet up again sometime.","\n","end",{"#f":5}],"c-1":["\n","ev",{"f()":"AnnoyedResponse"},"pop","/ev","\n","^I've been having a decent time up until this point but I think you should leave now. Send me a message if you change your mind. ","end","\n",{"#f":5}]}],{"#f":5}]}],{"#f":5}],"c-1":["^ ","\n","ev",{"f()":"NeutralResponse"},"pop","/ev","\n","^They didn't accept it and they made zero effort to try to understand me. My parents are somewhat conservative in some areas. The misgendering, constant use of my deadname and belittling remarks got to me in the end.","\n",["ev","str","^That's rough","/str","/ev",{"*":".^.c-0","flg":20},"ev","str","^ Maybe you deserved it","/str","/ev",{"*":".^.c-1","flg":20},{"c-0":["\n","ev",{"f()":"SmileResponse"},"pop","/ev","\n","^Sorry, I kinda ruined the vibe I think it's best we part ways for today. Send me a message if you wanna meet up again sometime. ","end","\n",{"#f":5}],"c-1":["\n","ev",{"f()":"Death"},"pop","/ev","\n","^That's it, I've had enough of you, just leave. ","end","\n",{"#f":5}]}],{"#f":5}]}],{"#f":5}],"c-1":["\n","^My parents are somewhat conservative in some areas. The misgendering, constant use of my deadname and belittling remarks got to me in the end.","\n",["ev","str","^That's rough","/str","/ev",{"*":".^.c-0","flg":20},"ev","str","^ Maybe you deserved it","/str","/ev",{"*":".^.c-1","flg":20},{"c-0":["\n","ev",{"f()":"SmileResponse"},"pop","/ev","\n","^Sorry, I kinda ruined the vibe I think it's best we part ways for today. Send me a message if you wanna meet up again sometime. ","end","\n",{"#f":5}],"c-1":["\n","ev",{"f()":"Death"},"pop","/ev","\n","end","^_","\n","^That's it, I've had enough of you, just leave. ","end","\n","end",{"#f":5}]}],{"#f":5}]}],{"#f":1}],"Death":["ev",{"VAR?":"loveAmount"},500,"-",{"VAR=":"loveAmount","re":true},"/ev",{"#f":1}],"EmbarrassedResponse":["ev","str","^Blush","/str","/ev",{"VAR=":"charEmotion","re":true},{"#f":1}],"NeutralResponse":["ev","str","^Neutral","/str","/ev",{"VAR=":"charEmotion","re":true},{"#f":1}],"SmileResponse":["ev",{"VAR?":"loveAmount"},2,"+",{"VAR=":"loveAmount","re":true},"/ev","ev","str","^Smile","/str","/ev",{"VAR=":"charEmotion","re":true},{"#f":1}],"HappyResponse":["ev",{"VAR?":"loveAmount"},1,"+",{"VAR=":"loveAmount","re":true},"/ev","ev","str","^Happy","/str","/ev",{"VAR=":"charEmotion","re":true},{"#f":1}],"AnnoyedResponse":["ev",{"VAR?":"loveAmount"},1,"-",{"VAR=":"loveAmount","re":true},"/ev","ev","str","^Annoyed","/str","/ev",{"VAR=":"charEmotion","re":true},{"#f":1}],"AnnoyedResponsee":["ev",{"VAR?":"loveAmount"},20,"-",{"VAR=":"loveAmount","re":true},"/ev","ev","str","^Annoyed","/str","/ev",{"VAR=":"charEmotion","re":true},{"#f":1}],"NegativeResponse":["ev",{"VAR?":"loveAmount"},2,"-",{"VAR=":"loveAmount","re":true},"/ev","ev","str","^Mad","/str","/ev",{"VAR=":"charEmotion","re":true},{"#f":1}],"global decl":["ev","str","^Quinn","/str",{"VAR=":"charName"},"str","^Neutral","/str",{"VAR=":"charEmotion"},0,{"VAR=":"loveAmount"},"/ev","end",null],"#f":1}],"listDefs":{}}