{"inkVersion":21,"root":[["^Hey there you are! Did you find the book?","\n","ev","str","^Yes, here it is","/str","/ev",{"*":"0.c-0","flg":20},"ev","str","^I think so, is this the right one?","/str","/ev",{"*":"0.c-1","flg":20},{"c-0":["^ ",{"->":"INTRODUCTION"},"\n",{"->":"0.g-0"},{"#f":5}],"c-1":["\n","^Hmm, let me see. Yes, ",{"->":"INTRODUCTION"},"\n",{"->":"0.g-0"},{"#f":5}],"g-0":["done",{"#f":5}]}],"done",{"nextDate":[["^I'm sorry for not finding you a book. I guess we'll have to come back here sometime!","\n","ev","str","^Yeah, sound nice!","/str","/ev",{"*":".^.c-0","flg":20},"ev","str","^Maybe not here","/str","/ev",{"*":".^.c-1","flg":20},{"c-0":["\n","ev",{"f()":"HappyResponse"},"pop","/ev","\n","^Perfect. We could go somewere else to if you want!","\n",["ev","str","^Lets decide that later.","/str","/ev",{"*":".^.c-0","flg":20},"ev","str","^I think I would like that more","/str","/ev",{"*":".^.c-1","flg":20},{"c-0":["\n","ev",{"f()":"HappyResponse"},"pop","/ev","\n","^Yeah sounds perfect. I had a great time today! Bye for now. ","end","\n",{"#f":5}],"c-1":["\n","^Oh, thats fine. I had a great time but I get that it's not for everyone. I hope to see you around. Bye! ","end","\n",{"#f":5}]}],{"#f":5}],"c-1":["\n","^Oh, sure I guess. My bad, I thought it was a nice place for a date.","\n",["ev","str","^It was alright","/str","/ev",{"*":".^.c-0","flg":20},"ev","str","^Not really my cup of tea","/str","/ev",{"*":".^.c-1","flg":20},{"c-0":["\n","^Well, we can go somewhere else for the next date!","\n",["ev","str","^Next date?","/str","/ev",{"*":".^.c-0","flg":20},{"c-0":["\n","ev",{"f()":"BlushResponse"},"pop","/ev","\n","^Well only if you want.","\n",["ev","str","^Yes","/str","/ev",{"*":".^.c-0","flg":20},"ev","str","^Let's see how we feel after the date","/str","/ev",{"*":".^.c-1","flg":20},{"c-0":["\n","ev",{"f()":"HappyResponse"},"pop","/ev","\n","^Great! Can't wait! ","end","\n",{"#f":5}],"c-1":["\n","ev",{"f()":"SadResponse"},"pop","/ev","\n","^Oh okay, sure. I guess i'll see you around..","\n","^Bye for now!","\n",["ev","str","^Bye","/str","/ev",{"*":".^.c-0","flg":20},{"c-0":["\n","end",{"#f":5}]}],{"#f":5}]}],{"#f":5}]}],{"#f":5}],"c-1":["\n","^Ah I see. Okay, thats fine. We can go somewhere else for the next date.","\n",["ev","str","^Next date?","/str","/ev",{"*":".^.c-0","flg":20},{"c-0":["\n","ev",{"f()":"BlushResponse"},"pop","/ev","\n","^Well only if you want.","\n",["ev","str","^Yes","/str","/ev",{"*":".^.c-0","flg":20},"ev","str","^Let's see how we feel after the date","/str","/ev",{"*":".^.c-1","flg":20},{"c-0":["\n","ev",{"f()":"HappyResponse"},"pop","/ev","\n","^Great! Can't wait! I'm gonna head home now! Bye for now!","\n",["ev","str","^Bye","/str","/ev",{"*":".^.c-0","flg":20},{"c-0":["\n","end",{"#f":5}]}],{"#f":5}],"c-1":["\n","ev",{"f()":"SadResponse"},"pop","/ev","\n","^Oh okay, sure. I guess i'll see you around..","\n","^Bye for now!","\n",["ev","str","^Bye","/str","/ev",{"*":".^.c-0","flg":20},{"c-0":["\n","end",{"#f":5}]}],{"#f":5}]}],{"#f":5}]}],{"#f":5}]}],{"#f":5}]}],{"#f":1}],"INTRODUCTION":[["^Perfect, thank you! I'll definitely put this book to good use.","\n","ev","str","^I hope so! I'm sure a book about a toxic plant is something everyone could use right?","/str","/ev",{"*":".^.c-0","flg":20},"ev","str","^Good! It took a lot of effort to find it.","/str","/ev",{"*":".^.c-1","flg":20},{"c-0":["\n","ev",{"f()":"SmileResponse"},"pop","/ev","\n","^Yes exactly! I appreciate your sense of humour.","\n",["ev","str","^So, why did you need the book?","/str","/ev",{"*":".^.c-0","flg":20},"ev","str","^But it's a little strange that you needed a book about a poisonous plant.","/str","/ev",{"*":".^.c-1","flg":20},{"c-0":["\n","^Oh, it's for an experiment that I've been working on. I'm hoping to be able to write a thesis about it if I succed. But enough about that! Look at the book I found!","\n",["ev","str","^You found another book?","/str","/ev",{"*":".^.c-0","flg":20},"ev","str","^What did you find???","/str","/ev",{"*":".^.c-1","flg":20},{"c-0":["\n","ev",{"f()":"SmileResponse"},"pop","/ev","\n","^Yes! I've been looking for this book forever! ",{"->":"RomanEmpire"},"\n",{"#f":5}],"c-1":["\n","ev",{"f()":"NeutralResponse"},"pop","/ev","\n","^This! I've been looking for this forever! ",{"->":"RomanEmpire"},"\n",{"#f":5}]}],{"#f":5}],"c-1":["\n","ev",{"f()":"AnnoyedResponse"},"pop","/ev","\n","^Huh? Well it's for an experiment that I've been working on.","\n",["ev","str","^Experiment?","/str","/ev",{"*":".^.c-0","flg":20},"ev","str","^Oh, okay","/str","/ev",{"*":".^.c-1","flg":20},{"c-0":["\n","ev",{"f()":"NeutralResponse"},"pop","/ev","\n","^Yes, It's hard to explain! It's for a project in school. However I did also find  another book! I've been looking for this book for forever! ",{"->":"RomanEmpire"},"\n",{"#f":5}],"c-1":["\n","ev",{"f()":"HappyResponse"},"pop","/ev","\n","^Yeah but look at the book I found! I've been looking for this book for forever.","\n",{"->":"RomanEmpire"},{"#f":5}]}],{"#f":5}]}],{"#f":5}],"c-1":["\n","ev",{"f()":"SmileResponse"},"pop","/ev","\n","^I'm sorry I should have helped more. I got distracted and forgot what I was looking for. Thank you for helping me! However when you were helping me I did find a couple of other books aswell. I have been looking for this book in particular for ages and then, there it was! Right in front of me!","\n",["ev","str","^Wait... You didn't want the book I spent half an hour looking for? ","/str","/ev",{"*":".^.c-0","flg":20},"ev","str","^Oh fun! What book did you find?","/str","/ev",{"*":".^.c-1","flg":20},{"c-0":["\n","ev",{"f()":"AnnoyedResponse"},"pop","/ev","\n","^What? No of course I did but I've been looking for this book for months! I was just excited about it.","\n",["ev","str","^Well, what is this book about then?","/str","/ev",{"*":".^.c-0","flg":20},{"c-0":["\n","ev",{"f()":"NeutralResponse"},"pop","/ev","\n",{"->":"RomanEmpire"},{"#f":5}]}],{"#f":5}],"c-1":["\n","ev",{"f()":"HappyResponse"},"pop","/ev","\n",{"->":"RomanEmpire"},{"#f":5}]}],{"#f":5}]}],{"#f":1}],"ANOTHERBOOK":[["^I found this other book as well.","\n","ev","str","^Oh, is it about the ancient greeks?","/str","/ev",{"*":".^.c-0","flg":20},{"c-0":["\n","ev","str","^Annoyed","/str","/ev",{"VAR=":"charEmotion","re":true},"^No, why would I ever read about that?","\n",["ev","str","^Oh, sorry just thought it fit","/str","/ev",{"*":".^.c-0","flg":20},"ev","str","^My bad, What is it about then?","/str","/ev",{"*":".^.c-1","flg":20},{"c-0":["\n","ev",{"f()":"HappyResponse"},"pop","/ev","\n","^It doesn't but I guess I can see how you got there. No, this book is for school. It's about microorganisms in alges. It's for a class I have. Did you find something for yourself?","\n",["ev","str","^No, I forgot to look..","/str","/ev",{"*":".^.c-0","flg":20},"ev","str","^Well, I was busy looking for your book","/str","/ev",{"*":".^.c-1","flg":20},{"c-0":["\n",{"->":"nextDate"},{"#f":5}],"c-1":["\n","ev",{"f()":"BlushResponse"},"pop","/ev","\n","^Oh right! Sorry. I didn't mean for it to become all about me. I have a tendency to loose myself in books.","\n",["ev","str","^Don't worry about it!","/str","/ev",{"*":".^.c-0","flg":20},{"c-0":[{"->":"nextDate"},"\n",{"#f":5}]}],{"#f":5}]}],{"#f":5}],"c-1":["\n","ev",{"f()":"NeutralResponse"},"pop","/ev","\n","^This is a book about microorganisms. They are so fascinating!","\n",["ev","str","^Microorganisms?","/str","/ev",{"*":".^.c-0","flg":20},"ev","str","^Wow, why?","/str","/ev",{"*":".^.c-1","flg":20},"ev","str","^No I had no idea!","/str","/ev",{"*":".^.c-2","flg":20},{"c-0":["\n","ev",{"f()":"ContentResponse"},"pop","/ev","\n","^Yeah, I'm studying to be a mircrobiolgist so it's helpful for school.","\n",["ev","str","^Ah okay, sounds interesting","/str","/ev",{"*":".^.c-0","flg":20},"ev","str","^Sounds difficult","/str","/ev",{"*":".^.c-1","flg":20},{"c-0":["\n","^Well sometimes. ",{"->":"nextDate"},"\n",{"#f":5}],"c-1":["\n","^Well it can be, but I really love what I study so.","\n",{"->":"nextDate"},{"#f":5}]}],{"#f":5}],"c-1":["\n","ev",{"f()":"NeutralResponse"},"pop","/ev","\n","^What do you mean why?","\n",["ev","str","^Why would you get a book about microorganisms?","/str","/ev",{"*":".^.c-0","flg":20},{"c-0":["\n","ev",{"f()":"SmileResponse"},"pop","/ev","\n","^It's for school. Sorry I'm only talking about myself here! Did you atleast find a book you liked?","\n",["ev","str","^No, I forgot to look","/str","/ev",{"*":".^.c-0","flg":20},"ev","str","^Not really, I was busy looking for you book","/str","/ev",{"*":".^.c-1","flg":20},{"c-0":["^  ",{"->":"nextDate"},"\n",{"#f":5}],"c-1":["\n","ev",{"f()":"BlushResponse"},"pop","/ev","\n","^Oh right! Sorry. I didn't mean for it to become all about me. I have a tendency to loose myself in books.","\n",["ev","str","^Don't worry about it!","/str","/ev",{"*":".^.c-0","flg":20},{"c-0":[{"->":"nextDate"},"\n","ev",{"f()":"SmileResponse"},"pop","/ev","\n",{"#f":5}]}],{"#f":5}]}],{"#f":5}]}],{"#f":5}],"c-2":["\n","ev","str","^Happy","/str","/ev",{"VAR=":"charEmotion","re":true},"^Well we are studying them in class right now and I needed the book to pass.","\n",["ev","str","^What about the book that I found?","/str","/ev",{"*":".^.c-0","flg":20},"ev","str","^Makes sense","/str","/ev",{"*":".^.c-1","flg":20},{"c-0":["\n","ev",{"f()":"SmileResponse"},"pop","/ev","\n","^Yes that one too, but it's for another class.","\n","^When you were looking did you find any book you liked?","\n",["ev","str","^No, I forgot to look","/str","/ev",{"*":".^.c-0","flg":20},"ev","str","^Well, I was busy looking for you book","/str","/ev",{"*":".^.c-1","flg":20},{"c-0":["^  ",{"->":"nextDate"},"\n",{"#f":5}],"c-1":["\n","ev",{"f()":"BlushResponse"},"pop","/ev","\n","^Oh right! Sorry. I didn't mean for it to become all about me. I have a tendency to lose my self in books.","\n",["ev","str","^Don't worry about it!","/str","/ev",{"*":".^.c-0","flg":20},{"c-0":[{"->":"nextDate"},"\n",{"#f":5}]}],{"#f":5}]}],{"#f":5}],"c-1":["\n","ev",{"f()":"NeutralResponse"},"pop","/ev","\n","^Yeah. When you were looking did you find any books you liked?","\n",["ev","str","^No, I forgot to look","/str","/ev",{"*":".^.c-0","flg":20},"ev","str","^Well, I was busy looking for you book","/str","/ev",{"*":".^.c-1","flg":20},{"c-0":["^  ",{"->":"nextDate"},"\n",{"#f":5}],"c-1":["\n","ev",{"f()":"BlushResponse"},"pop","/ev","\n","^Oh right! Sorry. I didn't mean for it to become all about me. I have a tendency to loose myself in books.","\n",["ev","str","^Don't worry about it!","/str","/ev",{"*":".^.c-0","flg":20},{"c-0":[{"->":"nextDate"},"\n","^=","\n",{"#f":5}]}],{"#f":5}]}],{"#f":5}]}],{"#f":5}]}],{"#f":5}]}],{"#f":5}]}],{"#f":1}],"RomanEmpire":[["^It's about the Roman Empire.","\n","ev","str","^I'm sorry what?","/str","/ev",{"*":".^.c-0","flg":20},"ev","str","^Oh like a fiction played out during the roman empire? Fun!","/str","/ev",{"*":".^.c-1","flg":20},"ev","str","^Why would you get a book about the Roman Empire?","/str","/ev",{"*":".^.c-2","flg":20},{"c-0":["\n","ev","str","^Happy","/str","/ev",{"VAR=":"charEmotion","re":true},"^The Roman Empire! You know the most influencial civilication ever! The book I found is one of the biggest deep dives into their law and culture yet!","\n",["ev","str","^Fun...","/str","/ev",{"*":".^.c-0","flg":20},"ev","str","^Oh, that's interesting","/str","/ev",{"*":".^.c-1","flg":20},{"c-0":["\n","ev",{"f()":"SmileResponse"},"pop","/ev","\n","^Yes so fun! I can't wait to read it. Did you know that the law they created back then has affected our socities laws today! Isn't it incredible that a socity so long ago still has influence over us today?","\n",["ev","str","^ You seem to know alot about this","/str","/ev",{"*":".^.c-0","flg":20},{"c-0":["\n","ev","str","^Blush","/str","/ev",{"VAR=":"charEmotion","re":true},"^Well yes! it's important to look back at what society was like then and see how it effects us today.","\n",["ev","str","^Hmm, And how often do you think about the Roman Empire?","/str","/ev",{"*":".^.c-0","flg":20},"ev","str","^Yeah, I suppose","/str","/ev",{"*":".^.c-1","flg":20},{"c-0":["\n","ev",{"f()":"NeutralResponse"},"pop","/ev","\n","^What do you mean? Like on a weekly basis? Or in general per day? Because it varies alot! Why? Do you not think about it?","\n",["ev","str","^I might start now","/str","/ev",{"*":".^.c-0","flg":20},"ev","str","^No, not since my last history class.","/str","/ev",{"*":".^.c-1","flg":20},{"c-0":["\n","ev",{"f()":"SmileResponse"},"pop","/ev","\n","^You should! I could show you some books that might help. I have a few a home that you could borrow.","\n",["ev","str","^sounds cool","/str","/ev",{"*":".^.c-0","flg":20},"ev","str","^We'll see","/str","/ev",{"*":".^.c-1","flg":20},"ev","str","^No, Thank you though","/str","/ev",{"*":".^.c-2","flg":20},{"c-0":["\n",{"->":"ANOTHERBOOK"},{"#f":5}],"c-1":["\n","ev",{"f()":"AnnoyedResponse"},"pop","/ev","\n","^You don't sound so sure but whatever. Anyways, ",{"->":"ANOTHERBOOK"},"\n",{"#f":5}],"c-2":["\n","ev",{"f()":"MadResponse"},"pop","/ev","\n","^Oh, okay, I guess it's not for everyone. Sorry, I tend to get stuck on subjects that really interest me. Anyways ",{"->":"ANOTHERBOOK"},"\n",{"#f":5}]}],{"#f":5}],"c-1":["\n","ev",{"f()":"NeutralResponse"},"pop","/ev","\n","^Well I could tell you all that you need to know about it but it might take a while. Plus I would need to prepare so that I don't miss anything important!","\n",["ev","str","^Bummer, maybe next time","/str","/ev",{"*":".^.c-0","flg":20},"ev","str","^I honestly would prefer if you didn't ","/str","/ev",{"*":".^.c-1","flg":20},"ev","str","^Yeah sound fun","/str","/ev",{"*":".^.c-2","flg":20},{"c-0":["\n","^Sound like a plan! Anyways, ",{"->":"ANOTHERBOOK"},"\n",{"#f":5}],"c-1":["\n","ev",{"f()":"AnnoyedResponse"},"pop","/ev","\n","^Whatever. I guess you'll never know then. Oh well. By the way, ",{"->":"ANOTHERBOOK"},"\n",{"#f":5}],"c-2":["\n","ev",{"f()":"HappyResponse"},"pop","/ev","\n","^Right! Anyways, ",{"->":"ANOTHERBOOK"},"\n",{"#f":5}]}],{"#f":5}]}],{"#f":5}],"c-1":["\n","^What? Do you not think about it?","\n",["ev","str","^I might start now","/str","/ev",{"*":".^.c-0","flg":20},"ev","str","^No, not since my last history class.","/str","/ev",{"*":".^.c-1","flg":20},{"c-0":["\n","ev",{"f()":"HappyResponse"},"pop","/ev","\n","^You should! I could show you some books that might help. I have a few a home that you could borrow.","\n",["ev","str","^Sounds cool","/str","/ev",{"*":".^.c-0","flg":20},"ev","str","^We'll see","/str","/ev",{"*":".^.c-1","flg":20},"ev","str","^No, Thank you though","/str","/ev",{"*":".^.c-2","flg":20},{"c-0":["\n",{"->":"ANOTHERBOOK"},{"#f":5}],"c-1":["\n","ev",{"f()":"AnnoyedResponse"},"pop","/ev","\n","^You don't sound so sure but whatever. Anyways, ",{"->":"ANOTHERBOOK"},"\n",{"#f":5}],"c-2":["\n","ev",{"f()":"NeutralResponse"},"pop","/ev","\n","^Oh, okay, I guess it's not for everyone. Sorry, I tend to get stuck on subjects that really interest me. Anyways ",{"->":"ANOTHERBOOK"},"\n",{"#f":5}]}],{"#f":5}],"c-1":["\n","ev",{"f()":"NeutralResponse"},"pop","/ev","\n","^Well I could tell you all that you need to know about it, but it might take a while. Plus I would need to prepare so that I don't miss anything important!","\n",["ev","str","^Bummer, maybe next time","/str","/ev",{"*":".^.c-0","flg":20},"ev","str","^I honestly would prefer if you didn't ","/str","/ev",{"*":".^.c-1","flg":20},"ev","str","^Yeah sound fun","/str","/ev",{"*":".^.c-2","flg":20},{"c-0":["\n","^Sound like a plan! Anyways, ",{"->":"ANOTHERBOOK"},"\n",{"#f":5}],"c-1":["\n","ev",{"f()":"MadResponse"},"pop","/ev","\n","^Whatever. I guess you'll never know then. Oh well. By the way, ",{"->":"ANOTHERBOOK"},"\n",{"#f":5}],"c-2":["\n","ev",{"f()":"SmileResponse"},"pop","/ev","\n","^Right! Anyways, ",{"->":"ANOTHERBOOK"},"\n",{"#f":5}]}],{"#f":5}]}],{"#f":5}]}],{"#f":5}]}],{"#f":5}],"c-1":["\n","ev",{"f()":"HappyResponse"},"pop","/ev","\n","^Right! This book is so hard to find. I can't believe it was right in front of me the whole time! Isn't it incredible that a society so long ago still has influence over us today!","\n",["ev","str","^Sure? You seem to know alot about this","/str","/ev",{"*":".^.c-0","flg":20},"ev","str","^Why would I care about the Roman Empire","/str","/ev",{"*":".^.c-1","flg":20},{"c-0":["\n","ev",{"f()":"NeutralResponse"},"pop","/ev","\n","^Well yes! it's important to look back at what society was like","\n","^then and see how it affects us today.","\n",["ev","str","^I never really thought about it like that before","/str","/ev",{"*":".^.c-0","flg":20},"ev","str","^How often do you think about the Roman Empire?","/str","/ev",{"*":".^.c-1","flg":20},{"c-0":["\n","ev",{"f()":"HappyResponse"},"pop","/ev","\n","^Well lucky for you that you found me! I think about alot. It's so advanced for existing when it did.","\n",["ev","str","^You think about the Roman Empire alot?","/str","/ev",{"*":".^.c-0","flg":20},{"c-0":["\n","ev",{"f()":"ConfusedResponse"},"pop","/ev","\n","^Yeah all the time! You don't?","\n",["ev","str","^I might start now","/str","/ev",{"*":".^.c-0","flg":20},"ev","str","^no, not since my last history class.","/str","/ev",{"*":".^.c-1","flg":20},{"c-0":["\n","ev",{"f()":"SmileResponse"},"pop","/ev","\n","^You should!I could show you some books that might help","\n",["ev","str","^I honestly would prefer if you didn't ","/str","/ev",{"*":".^.c-0","flg":20},"ev","str","^Yeah sound fun","/str","/ev",{"*":".^.c-1","flg":20},{"c-0":["\n","^Whatever. I guess you'll never know then. Oh well. By the way, ",{"->":"ANOTHERBOOK"},"\n",{"#f":5}],"c-1":["\n","^Right! Anyways, ",{"->":"ANOTHERBOOK"},"\n",{"#f":5}]}],{"#f":5}],"c-1":["\n","ev",{"f()":"ConfusedResponse"},"pop","/ev","\n","^Well I could tell you all that you need to know about it but it would take a while and i would need to prepare so that I don't miss anything important!","\n",["ev","str","^Bummer, maybe next time","/str","/ev",{"*":".^.c-0","flg":20},"ev","str","^Honestly I would prefer to skip it","/str","/ev",{"*":".^.c-1","flg":20},{"c-0":["\n","^Sure! Anyways, ",{"->":"ANOTHERBOOK"},"\n",{"#f":5}],"c-1":["\n","ev",{"f()":"AnnoyedResponse"},"pop","/ev","\n","^Oh sure I guess that's fine.","\n",["ev","str","^Did you find anything else?","/str","/ev",{"*":".^.c-0","flg":20},"ev","str","^So, what now?","/str","/ev",{"*":".^.c-1","flg":20},{"c-0":["\n","ev",{"f()":"HappyResponse"},"pop","/ev","\n","^Ah yes! ",{"->":"ANOTHERBOOK"},"\n",{"#f":5}],"c-1":["\n","ev",{"f()":"NeutralResponse"},"pop","/ev","\n","^Well, I guess I'm gonna go and pay for the books. Actually, ",{"->":"ANOTHERBOOK"},"\n",{"#f":5}]}],{"#f":5}]}],{"#f":5}]}],{"#f":5}]}],{"#f":5}],"c-1":["\n","^Like on a weekly basis? Or times per day?","\n","ev","str","^Neutral","/str","/ev",{"VAR=":"charEmotion","re":true},["ev","str","^You think about it more than once a day!","/str","/ev",{"*":".^.c-0","flg":20},"ev","str","^I see","/str","/ev",{"*":".^.c-1","flg":20},{"c-0":["\n","ev",{"f()":"ConfusedResponse"},"pop","/ev","\n","^Well, depends on the week and what I'm doing. Why? Is it strange? how often do you think about it?","\n",["ev","str","^I might start now","/str","/ev",{"*":".^.c-0","flg":20},"ev","str","^No, not since my last history class.","/str","/ev",{"*":".^.c-1","flg":20},{"c-0":["\n","ev",{"f()":"HappyResponse"},"pop","/ev","\n","^You should! I could show you some books that might help","\n",["ev","str","^I honestly I would prefer if you didn't ","/str","/ev",{"*":".^.c-0","flg":20},"ev","str","^Yeah sound fun","/str","/ev",{"*":".^.c-1","flg":20},{"c-0":["\n","ev",{"f()":"AnnoyedResponse"},"pop","/ev","\n","^Whatever. I guess you'll never know then. Oh well. By the way, ",{"->":"ANOTHERBOOK"},"\n",{"#f":5}],"c-1":["\n","ev",{"f()":"HappyResponse"},"pop","/ev","\n","^Right! Anyways, ",{"->":"ANOTHERBOOK"},"\n",{"#f":5}]}],{"#f":5}],"c-1":["\n","ev",{"f()":"ConfusedResponse"},"pop","/ev","\n","^What! Well I could tell you all that you need to know about it, but it would take a while, and I would need to prepare so that I don't miss anything important!","\n",["ev","str","^Bummer, maybe next time","/str","/ev",{"*":".^.c-0","flg":20},"ev","str","^Honstly I would prefer to skip it","/str","/ev",{"*":".^.c-1","flg":20},{"c-0":["\n","ev",{"f()":"NeutralResponse"},"pop","/ev","\n","^sure! Anyways, ",{"->":"ANOTHERBOOK"},"\n",{"#f":5}],"c-1":["\n","ev",{"f()":"AnnoyedResponse"},"pop","/ev","\n","^Oh sure I guess that's fine.","\n",["ev","str","^Did you find anything else?","/str","/ev",{"*":".^.c-0","flg":20},"ev","str","^So, what now?","/str","/ev",{"*":".^.c-1","flg":20},{"c-0":["\n","^Ah yes! ",{"->":"ANOTHERBOOK"},"\n",{"#f":5}],"c-1":["\n","ev",{"f()":"NeutralResponse"},"pop","/ev","\n","^Well, I guess I'm gonna go and pay for the books. Actually, ",{"->":"ANOTHERBOOK"},"\n",{"#f":5}]}],{"#f":5}]}],{"#f":5}]}],{"#f":5}],"c-1":["\n","ev",{"f()":"ConfusedResponse"},"pop","/ev","\n","^Why? Don't you think about it?","\n",["ev","str","^I might start now","/str","/ev",{"*":".^.c-0","flg":20},"ev","str","^no, not since my last history class.","/str","/ev",{"*":".^.c-1","flg":20},{"c-0":["\n","ev",{"f()":"HappyResponse"},"pop","/ev","\n","^You should!I could show you some books that might help","\n",["ev","str","^I honestly would prefer if you didn't ","/str","/ev",{"*":".^.c-0","flg":20},"ev","str","^Yeah sound fun!","/str","/ev",{"*":".^.c-1","flg":20},{"c-0":["\n","ev",{"f()":"AnnoyedResponse"},"pop","/ev","\n","^Whatever. I guess you'll never know then. Oh well. By the way, ",{"->":"ANOTHERBOOK"},"\n",{"#f":5}],"c-1":["\n","ev",{"f()":"SmileResponse"},"pop","/ev","\n","^Right! Anyways, ",{"->":"ANOTHERBOOK"},"\n",{"#f":5}]}],{"#f":5}],"c-1":["\n","ev",{"f()":"ConfusedResponse"},"pop","/ev","\n","^Well I could tell you all that you need to know about it but it would take a while and i would need to prepare so that I don't miss anything important!","\n",["ev","str","^Bummer, maybe next time","/str","/ev",{"*":".^.c-0","flg":20},"ev","str","^Honestly, I would prefer to skip it","/str","/ev",{"*":".^.c-1","flg":20},{"c-0":["\n","ev",{"f()":"NeutralResponse"},"pop","/ev","\n","^Sure! Anyways, ",{"->":"ANOTHERBOOK"},"\n",{"#f":5}],"c-1":["\n","ev",{"f()":"SadResponse"},"pop","/ev","\n","^Oh sure, I guess that's fine.","\n",["ev","str","^Did you find anything else?","/str","/ev",{"*":".^.c-0","flg":20},"ev","str","^So, what now?","/str","/ev",{"*":".^.c-1","flg":20},{"c-0":["\n","ev",{"f()":"HappyResponse"},"pop","/ev","\n","^Ah yes! ",{"->":"ANOTHERBOOK"},"\n",{"#f":5}],"c-1":["\n","ev",{"f()":"NeutralResponse"},"pop","/ev","\n","^Well, I guess I'm gonna go and pay for the books. Actually, ",{"->":"ANOTHERBOOK"},"\n",{"#f":5}]}],{"#f":5}]}],{"#f":5}]}],{"#f":5}]}],{"#f":5}]}],{"#f":5}],"c-1":["\n","ev",{"f()":"MadResponse"},"pop","/ev","\n","^why wouldn't you!? It's the most influencial civilzation ever existing! it's worth to atleast think about!","\n",["ev","str","^Huh! And how often do you think about the Roman Empire?","/str","/ev",{"*":".^.c-0","flg":20},{"c-0":["\n","ev",{"f()":"NeutralResponse"},"pop","/ev","\n","^Like weekly? or in general per day? Do you not think about it?","\n",["ev","str","^I might start now","/str","/ev",{"*":".^.c-0","flg":20},"ev","str","^No, not since my last history class.","/str","/ev",{"*":".^.c-1","flg":20},{"c-0":["\n","ev",{"f()":"HappyResponse"},"pop","/ev","\n","^You should! I could show you some books that might help.","\n",["ev","str","^I honestly would prefer if you didn't ","/str","/ev",{"*":".^.c-0","flg":20},"ev","str","^Yeah sound fun","/str","/ev",{"*":".^.c-1","flg":20},{"c-0":["\n","ev",{"f()":"AnnoyedResponse"},"pop","/ev","\n","^Whatever. I guess you'll never know then. Oh well. By the way, ",{"->":"ANOTHERBOOK"},"\n",{"#f":5}],"c-1":["\n","ev",{"f()":"HappyResponse"},"pop","/ev","\n","^Right! Anyways, ",{"->":"ANOTHERBOOK"},"\n",{"#f":5}]}],{"#f":5}],"c-1":["\n","ev",{"f()":"NeutralResponse"},"pop","/ev","\n","^Well I could tell you all that you need to know about it, but it would take a while, and I would need to prepare so that I don't miss anything important!","\n",["ev","str","^Bummer, maybe next time","/str","/ev",{"*":".^.c-0","flg":20},"ev","str","^Honestly I would prefer to skip it","/str","/ev",{"*":".^.c-1","flg":20},{"c-0":["\n","ev",{"f()":"NeutralResponse"},"pop","/ev","\n","^sure! Anyways, ",{"->":"ANOTHERBOOK"},"\n",{"#f":5}],"c-1":["\n","ev",{"f()":"AnnoyedResponse"},"pop","/ev","\n","^Oh sure I guess that's fine.","\n",["ev","str","^Did you find anything else?","/str","/ev",{"*":".^.c-0","flg":20},"ev","str","^So, what now?","/str","/ev",{"*":".^.c-1","flg":20},{"c-0":["\n","ev",{"f()":"HappyResponse"},"pop","/ev","\n","^Ah yes! ",{"->":"ANOTHERBOOK"},"\n",{"#f":5}],"c-1":["\n","ev",{"f()":"NeutralResponse"},"pop","/ev","\n","^Well I guess I'm gonna go and pay for the books. actually ",{"->":"ANOTHERBOOK"},"\n",{"#f":5}]}],{"#f":5}]}],{"#f":5}]}],{"#f":5}]}],{"#f":5}]}],{"#f":5}]}],{"#f":5}],"c-1":["\n","ev",{"f()":"NeutralResponse"},"pop","/ev","\n","^No I don't really read fiction. I think it just as bad as incorrect facts in movies.","\n",["ev","str","^What do you mean?","/str","/ev",{"*":".^.c-0","flg":20},{"c-0":["\n","ev","str","^Smile","/str","/ev",{"VAR=":"charEmotion","re":true},"^Well, you can just make up a fact about something just because you want it to fit your perception. A fact is a fact and we should be careful with what kind of information we spread.","\n",["ev","str","^Like about the Roman Empire?","/str","/ev",{"*":".^.c-0","flg":20},{"c-0":["\n","ev","str","^Neutral","/str","/ev",{"VAR=":"charEmotion","re":true},"^Exactly! it's already being incorrectly used in multiple books and movies. Especially fiction so that's why it's important with this book because it actually gives the correct information.","\n",["ev","str","^Huh, you seem to know alot about it","/str","/ev",{"*":".^.c-0","flg":20},{"c-0":["\n","ev",{"f()":"ContentResponse"},"pop","/ev","\n","^Well, there is alot to learn. I mean think about it!","\n",["ev","str","^How often do you think about the roman Empire?","/str","/ev",{"*":".^.c-0","flg":20},{"c-0":["\n","ev","str","^Confused","/str","/ev",{"VAR=":"charEmotion","re":true},"^Like a day? Or weakly, because it depends. Why are you looking at me like that! like you don't think about it!","\n",["ev","str","^I might start now","/str","/ev",{"*":".^.c-0","flg":20},"ev","str","^No, not since my last history class.","/str","/ev",{"*":".^.c-1","flg":20},{"c-0":["\n","ev",{"f()":"HappyResponse"},"pop","/ev","\n","^You should!I could show you some books that might help","\n",["ev","str","^I honestly would prefer if you didn't ","/str","/ev",{"*":".^.c-0","flg":20},"ev","str","^Yeah, sounds fun!","/str","/ev",{"*":".^.c-1","flg":20},{"c-0":["\n","ev",{"f()":"AnnoyedResponse"},"pop","/ev","\n","^Whatever. I guess you'll never know then. Oh well. By the way, ",{"->":"ANOTHERBOOK"},"\n",{"#f":5}],"c-1":["\n","ev",{"f()":"BlushResponse"},"pop","/ev","\n","^Right! Anyways, ",{"->":"ANOTHERBOOK"},"\n",{"#f":5}]}],{"#f":5}],"c-1":["\n","ev",{"f()":"NeutralResponse"},"pop","/ev","\n","^Well I could tell you all that you need to know about it but it would take a while and i would need to prepare so that I don't miss anything important!","\n",["ev","str","^Bummer, maybe next time","/str","/ev",{"*":".^.c-0","flg":20},"ev","str","^Honestly I would prefer to skip it","/str","/ev",{"*":".^.c-1","flg":20},{"c-0":["\n","ev",{"f()":"SmileResponse"},"pop","/ev","\n","^Sure! Anyways, ",{"->":"ANOTHERBOOK"},"\n",{"#f":5}],"c-1":["\n","ev",{"f()":"AnnoyedResponse"},"pop","/ev","\n","^Oh sure I guess that's fine.","\n",["ev","str","^Did you find anything else?","/str","/ev",{"*":".^.c-0","flg":20},"ev","str","^So, what now?","/str","/ev",{"*":".^.c-1","flg":20},{"c-0":["\n","ev",{"f()":"NeutralResponse"},"pop","/ev","\n","^Ah yes! ",{"->":"ANOTHERBOOK"},"\n",{"#f":5}],"c-1":["\n","ev",{"f()":"NeutralResponse"},"pop","/ev","\n","^Well, I guess I'm gonna go and pay for the books. Actually, ",{"->":"ANOTHERBOOK"},"\n",{"#f":5}]}],{"#f":5}]}],{"#f":5}]}],{"#f":5}]}],{"#f":5}]}],{"#f":5}]}],{"#f":5}]}],{"#f":5}],"c-2":["\n","ev",{"f()":"NeutralResponse"},"pop","/ev","\n","^Well why wouldn't I? There is so much to learn from them! They were one of the most advanced civilzation at the time. It's fascinating!","\n",["ev","str","^It's not really my thing so...","/str","/ev",{"*":".^.c-0","flg":20},"ev","str","^I guess..","/str","/ev",{"*":".^.c-1","flg":20},{"c-0":["\n","ev",{"f()":"AnnoyedResponse"},"pop","/ev","\n","^Oh alright then. Well ",{"->":"ANOTHERBOOK"},"\n",{"#f":5}],"c-1":["\n","^I promise that it is! I can totally let you borrow some of my books about it if you'd like? I have some really good ones!","\n",["ev","str","^Sure sound fun!","/str","/ev",{"*":".^.c-0","flg":20},"ev","str","^No thanks","/str","/ev",{"*":".^.c-1","flg":20},{"c-0":["\n","ev",{"f()":"HappyResponse"},"pop","/ev","\n","^I'm glad you think so! ",{"->":"ANOTHERBOOK"},"\n",{"#f":5}],"c-1":["\n","ev",{"f()":"AnnoyedResponse"},"pop","/ev","\n","^Oh well that's disappointing. Oh Well! ",{"->":"ANOTHERBOOK"},"\n",{"#f":5}]}],{"#f":5}]}],{"#f":5}]}],{"#f":1}],"HappyResponse":["ev","str","^Happy","/str","/ev",{"VAR=":"charEmotion","re":true},"ev","str","^","/str","/ev",{"VAR=":"charSound","re":true},"ev",{"VAR?":"loveAmount"},1,"+",{"VAR=":"loveAmount","re":true},"/ev",{"#f":1}],"SadResponse":["ev","str","^Sad","/str","/ev",{"VAR=":"charEmotion","re":true},"ev","str","^","/str","/ev",{"VAR=":"charSound","re":true},"ev",{"VAR?":"loveAmount"},1,"-",{"VAR=":"loveAmount","re":true},"/ev",{"#f":1}],"NeutralResponse":["ev","str","^Neutral","/str","/ev",{"VAR=":"charEmotion","re":true},"ev","str","^","/str","/ev",{"VAR=":"charSound","re":true},{"#f":1}],"MadResponse":["ev","str","^Mad","/str","/ev",{"VAR=":"charEmotion","re":true},"ev","str","^","/str","/ev",{"VAR=":"charSound","re":true},"ev",{"VAR?":"loveAmount"},5,"-",{"VAR=":"loveAmount","re":true},"/ev",{"#f":1}],"AnnoyedResponse":["ev","str","^Annoyed","/str","/ev",{"VAR=":"charEmotion","re":true},"ev","str","^","/str","/ev",{"VAR=":"charSound","re":true},"ev",{"VAR?":"loveAmount"},1,"-",{"VAR=":"loveAmount","re":true},"/ev",{"#f":1}],"ContentResponse":["ev","str","^Content","/str","/ev",{"VAR=":"charEmotion","re":true},"ev","str","^","/str","/ev",{"VAR=":"charSound","re":true},"ev",{"VAR?":"loveAmount"},1,"+",{"VAR=":"loveAmount","re":true},"/ev",{"#f":1}],"SmileResponse":["ev","str","^Smile","/str","/ev",{"VAR=":"charEmotion","re":true},"ev","str","^","/str","/ev",{"VAR=":"charSound","re":true},"ev",{"VAR?":"loveAmount"},1,"+",{"VAR=":"loveAmount","re":true},"/ev",{"#f":1}],"ConfusedResponse":["ev","str","^Shocked","/str","/ev",{"VAR=":"charEmotion","re":true},"ev","str","^","/str","/ev",{"VAR=":"charSound","re":true},"ev",{"VAR?":"loveAmount"},1,"-",{"VAR=":"loveAmount","re":true},"/ev",{"#f":1}],"BlushResponse":["ev","str","^Blush","/str","/ev",{"VAR=":"charEmotion","re":true},"ev","str","^","/str","/ev",{"VAR=":"charSound","re":true},"ev",{"VAR?":"loveAmount"},1,"+",{"VAR=":"loveAmount","re":true},"/ev",{"#f":1}],"global decl":["ev","str","^Quinn","/str",{"VAR=":"charName"},"str","^Neutral","/str",{"VAR=":"charEmotion"},0,{"VAR=":"loveAmount"},"str","^","/str",{"VAR=":"charSound"},"/ev","end",null],"#f":1}],"listDefs":{}}